{
	"properties": "Properties",
	"editproperties": "Edit Properties",
	"remove": "Remove",
	"removeTemplates": "Remove Templates",
	"removeTemplatesMessage": "Do you want to remove the selected templates from the list ?",
	"export": "Export",
	"edit": "Open in Editor ",
	"duplicate": "Duplicate",
	"cancel": "Cancel",

	"commands.home": "Home",
	"commands.addTemplate": "Add Template",
	"commands.createTemplate": "Create Template",
	"commands.insertTemplate": "Add Existing Templates",
	"commands.import": "Import Templates",
	"commands.tileview": "Tile view",
	"commands.listview": "List view",

	"loader": "Loading...",
	"templateTypePref": "Default type",

	"editor.quit.title": "Unsaved modifications",
	"editor.quit.body": "Do you want to save modifications?",
	"editor.quit.save": "Save",
	"editor.quit.discard": "Discard",
	"editor.quit.cancel": "Cancel",

	"wpStartActivities": "Start Activities",
	"wpQuickAccess": "Quick Access",
	"createTemplate": "Create Template",
	"openTemplate": "Open Template",
	"viewTemplatesList": "Templates",
	"viewRecentObjects": "Recent Objects",

	"placeholder": "Drop template here",
	"placeholderButtonLabel": "Search for template",

	"INVALID_DATA": "Invalid data",
	"INVALID_FILE_FORMAT": "Invalid file format",

	"lifeCycle.IN WORK"   : "In Work",
	"lifeCycle.PRIVATE"   : "Private",
	"lifeCycle.FROZEN"    : "Frozen",
	"lifeCycle.RELEASED"  : "Released",
	"lifeCycle.OBSOLETE"  : "Obsolete",
	"newtemplate": "New Template",
	"title": "Title",
	"description": "Description",
	"create": "Create",
	"showMore": "Show More",
	"blankAutoName": "Leave blank for autoname",
	"name": "Name",
	"type": "Type",
	"revision": "Revision",
	"policy": "Policy",
	"owner": "Owner",
	"maturity_state": "Maturity State",
	"policyList": ["Report Model"],
	"errorTitle": "Title must be required!",
	"errrorResponse": "Business object 'type name revision' not unique",
	"uniqueError": "Type, Name or Revision must be unique",
	"errorMessage":"Cannot create the Template format",

	"otScript_Save":"Save",
	"otScript_CheckCode":"Check code",
	"otScript_Export":"Export",
	"otScript_New":"New",
	"otScript_addSnipetCode":"Insert an OTScript method example",
	"otScript_edit":"Edit ",
	"otScript_remove":"Remove",

	"templateUsed": "The following objects are still used: ${0}",
	"action": "Action",
	"openTemplateEditor": "Open with Template Editor",
	"parameters": "Parameters"

}


