{
  "singleUnit": "单位",
  "multipleUnits": "单位",
  "MATURITY_STATE": "成熟度状态",
  "information": "信息",
  "delete": "删除",
  "filter": "过滤",
  "OWNED_BY_ME": "归我所有",
  "OWNED_BY_MY_ORGANIZATIONS": "归我的组织所有",
  "plan": "计划",
  "SERIAL_NUMBER": "序列号",
  "MODEL_VERSION": "模型版本",
  "PRODUCT_CONFIGURATION": "产品配置",
  "MANUFACTURING_PLAN": "制造计划",
  "ACTUAL_BUILD_DATE": "实际制造日期",
  "PLANNED_BUILD_DATE": "计划制造日期",
  "DATE_SHIPPED": "发货日期",
  "Number_of_Units_to_create": "要创建的单位数",
  "description": "描述",
  "Error_Setting_Context": "设置上下文时出错",
  "Search_For_Model": "搜索模型",
  "Unit_Updated": "单位分配成功",
  "Unit_Update_Failed": "单位分配失败",
  "Units_Updated": "单位分配成功",
  "Units_Update_Failed": "单位分配失败",
  "ERR_CREATION_FAILED": "创建失败",
  "CREATION_SUCCESSFUL": "创建成功",
  "DELETION_SUCCESSFUL": "删除成功",
  "DELETION_FAILED": "删除失败",
  "UNIT_UPDATED": "单位已更新",
  "UNIT_UPDATION_FAILED": "单位更新失败",
  "Date_Updation_Successful": "日期更新成功",
  "Date_Updation_Failed": "日期更新失败",
  "Select_Product_Configuration": "选择产品配置",
  "Select_Manufacturing_Plan": "选择制造计划",
  "Select_Model_Version": "选择模型版本",
  "SAVE": "保存",
  "CANCEL": "取消",
  "CONTEXT_SELECTOR": "上下文选择器"
}
