{
  "multi_root_tile": " 요구 사항 루트",
  "csv_name": "requirement_structure_",
  "Requirement Group": "스펙 폴더",
  "ds6w:label": "표시 이름",
  "Transaction_forbidden": "트랜잭션 금지됨",
  "Reparent_done": "재정렬/상위 항목 재지정 완료",
  "InsertRequirementSpecification": "새 요구 사항 스펙 삽입",
  "InsertSpecificationFolder": "새 스펙 폴더 삽입",
  "InsertNew": "새로 삽입",
  "InsertRequirement": "새 요구 사항 삽입",
  "InsertComment": "새 코멘트 삽입",
  "InsertChapter": "새 장 삽입",
  "InsertExisting": "기존 개체 삽입",
  "InsertExistingRequirement": "기존 요구 사항 삽입",
  "InsertExistingRequirementSpecification": "기존 요구 사항 스펙 삽입",
  "InsertExistingSpecificationFolder": "기존 스펙 폴더 삽입",
  "InsertExistingChapter": "기존 챕터 삽입",
  "InsertExistingComment": "기존 코멘트 삽입",
  "StartLink": "시작 링크",
  "EndLink": "끝 링크",
  "DetachCommand": "분리",
  "msg_error_name_maxlength": "새 제목의 길이가 허용된 127자보다 더 깁니다.",
  "msg_error_name_badchars": "새 제목에 잘못된 문자가 있습니다.",
  "msg_error_name_empty": "제목은 비워 둘 수 없습니다.",
  "msg_error_name_no_title_in_displayname": "표시 이름에 제목이 없습니다. 제목을 수정할 수 있도록 ENOVIA 기본 설정을 수정하십시오.",
  "AddNew": "새로 추가",
  "AddRequirementSpecification": "새 요구 사항 스펙 추가",
  "AddSpecificationFolder": "새 스펙 폴더 추가",
  "AddRequirement": "새 요구 사항 추가",
  "AddComment": "새 코멘트 추가",
  "AddChapter": "새 챕터 추가",
  "Links_Management": "링크 관리",
  "PlmParameter": "파라미터",
  "paramContent": "파라미터 값",
  "insertParameterCommand": "새 파라미터 삽입",
  "ds6wg:requirement_category": "요구 사항 범주",
  "ExternalSubReq": "하위 요구 사항",
  "InsertExistExtReq": "외부 기존 요구 사항 삽입",
  "ExternalDerivedReq": "다운스트림 요구 사항",
  "InsertNewExtReq": "외부 새 요구 사항 삽입",
  "CMDCopy": "복사",
  "CMDCut": "잘라내기",
  "CMDPaste": "붙여넣기",
  "copyNonPSNode": "연결된 개체 {label}을(를) 복사할 수 없습니다.",
  "copyNonPSNodes": "{length}개의 연결된 개체를 복사할 수 없습니다. ",
  "composite": "실행 중...",
  "pasteObjectNotInView": " 앱에 없음",
  "reselectionFeedback": "데이터 일관성을 위해 입력 선택이 수정됨",
  "Thumbnail": "섬네일",
  "DataGridView": "데이터 그리드 보기",
  "Tile": "타일",
  "Title_empty": "제목 필드는 필수입니다. 값을 입력하십시오.",
  "Copy_Paste_Effectivity": "복사/붙여넣기 효력",
  "Mediocre": "중간",
  "Low": "낮음",
  "High": "높음",
  "Very High": "매우 높음",
  "Least Important": "중요도 가장 낮음",
  "Medium": "중간",
  "Pre-assigned": "사전 지정됨",
  "Urgent": "긴급",
  "CopyLink": "링크 복사"
}
